[
  {
    "Year": 1924,
    "NumAthletes": 460,
    "NumWomen": 17,
    "NumMale": 443
  },
  {
    "Year": 1928,
    "NumAthletes": 582,
    "NumWomen": 33,
    "NumMale": 549
  },
  {
    "Year": 1932,
    "NumAthletes": 352,
    "NumWomen": 22,
    "NumMale": 330
  },
  {
    "Year": 1936,
    "NumAthletes": 895,
    "NumWomen": 81,
    "NumMale": 814
  },
  {
    "Year": 1948,
    "NumAthletes": 1075,
    "NumWomen": 133,
    "NumMale": 942
  },
  {
    "Year": 1952,
    "NumAthletes": 1088,
    "NumWomen": 185,
    "NumMale": 903
  },
  {
    "Year": 1956,
    "NumAthletes": 1307,
    "NumWomen": 246,
    "NumMale": 1061
  },
  {
    "Year": 1960,
    "NumAthletes": 1116,
    "NumWomen": 295,
    "NumMale": 821
  },
  {
    "Year": 1964,
    "NumAthletes": 1778,
    "NumWomen": 404,
    "NumMale": 1374
  },
  {
    "Year": 1968,
    "NumAthletes": 1891,
    "NumWomen": 416,
    "NumMale": 1475
  },
  {
    "Year": 1972,
    "NumAthletes": 1655,
    "NumWomen": 415,
    "NumMale": 1240
  },
  {
    "Year": 1976,
    "NumAthletes": 1861,
    "NumWomen": 434,
    "NumMale": 1427
  },
  {
    "Year": 1980,
    "NumAthletes": 1746,
    "NumWomen": 430,
    "NumMale": 1316
  },
  {
    "Year": 1984,
    "NumAthletes": 2134,
    "NumWomen": 536,
    "NumMale": 1598
  },
  {
    "Year": 1988,
    "NumAthletes": 2639,
    "NumWomen": 680,
    "NumMale": 1959
  },
  {
    "Year": 1992,
    "NumAthletes": 3436,
    "NumWomen": 1054,
    "NumMale": 2382
  },
  {
    "Year": 1994,
    "NumAthletes": 3160,
    "NumWomen": 1105,
    "NumMale": 2055
  },
  {
    "Year": 1998,
    "NumAthletes": 3605,
    "NumWomen": 1384,
    "NumMale": 2221
  },
  {
    "Year": 2002,
    "NumAthletes": 4109,
    "NumWomen": 1582,
    "NumMale": 2527
  },
  {
    "Year": 2006,
    "NumAthletes": 4382,
    "NumWomen": 1757,
    "NumMale": 2625
  },
  {
    "Year": 2010,
    "NumAthletes": 4402,
    "NumWomen": 1847,
    "NumMale": 2555
  },
  {
    "Year": 2014,
    "NumAthletes": 4891,
    "NumWomen": 2023,
    "NumMale": 2868
  }
]